KeTidaiDeTuanduiLingxiuPeiyangJihua/README.md
KeTidaiDeTuanduiLingxiuPeiyangJihua/__init__.py
KeTidaiDeTuanduiLingxiuPeiyangJihua/__main__.py
KeTidaiDeTuanduiLingxiuPeiyangJihua/file.epub
KeTidaiDeTuanduiLingxiuPeiyangJihua/index.html
KeTidaiDeTuanduiLingxiuPeiyangJihua/css/__init__.py
KeTidaiDeTuanduiLingxiuPeiyangJihua/css/annotations.css
KeTidaiDeTuanduiLingxiuPeiyangJihua/css/main.css
KeTidaiDeTuanduiLingxiuPeiyangJihua/css/normalize.css
KeTidaiDeTuanduiLingxiuPeiyangJihua/css/popup.css
KeTidaiDeTuanduiLingxiuPeiyangJihua/font/__init__.py
KeTidaiDeTuanduiLingxiuPeiyangJihua/font/fontello.eot
KeTidaiDeTuanduiLingxiuPeiyangJihua/font/fontello.svg
KeTidaiDeTuanduiLingxiuPeiyangJihua/font/fontello.ttf
KeTidaiDeTuanduiLingxiuPeiyangJihua/font/fontello.woff
KeTidaiDeTuanduiLingxiuPeiyangJihua/img/__init__.py
KeTidaiDeTuanduiLingxiuPeiyangJihua/img/annotator-glyph-sprite.png
KeTidaiDeTuanduiLingxiuPeiyangJihua/img/annotator-icon-sprite.png
KeTidaiDeTuanduiLingxiuPeiyangJihua/img/apple-touch-icon.png
KeTidaiDeTuanduiLingxiuPeiyangJihua/img/cancelfullscreen.png
KeTidaiDeTuanduiLingxiuPeiyangJihua/img/close.png
KeTidaiDeTuanduiLingxiuPeiyangJihua/img/fullscreen.png
KeTidaiDeTuanduiLingxiuPeiyangJihua/img/loader.gif
KeTidaiDeTuanduiLingxiuPeiyangJihua/img/menu-icon.png
KeTidaiDeTuanduiLingxiuPeiyangJihua/img/save.png
KeTidaiDeTuanduiLingxiuPeiyangJihua/img/saved.png
KeTidaiDeTuanduiLingxiuPeiyangJihua/img/settings-s.png
KeTidaiDeTuanduiLingxiuPeiyangJihua/img/settings.png
KeTidaiDeTuanduiLingxiuPeiyangJihua/img/star.png
KeTidaiDeTuanduiLingxiuPeiyangJihua/js/__init__.py
KeTidaiDeTuanduiLingxiuPeiyangJihua/js/epub.js
KeTidaiDeTuanduiLingxiuPeiyangJihua/js/epub.min.js
KeTidaiDeTuanduiLingxiuPeiyangJihua/js/epub.min.map
KeTidaiDeTuanduiLingxiuPeiyangJihua/js/hooks.min.js
KeTidaiDeTuanduiLingxiuPeiyangJihua/js/hooks.min.map
KeTidaiDeTuanduiLingxiuPeiyangJihua/js/reader.js
KeTidaiDeTuanduiLingxiuPeiyangJihua/js/reader.js.map
KeTidaiDeTuanduiLingxiuPeiyangJihua/js/reader.min.js
ke_tidai_de_tuandui_lingxiu_peiyang_jihua-2024.3.1.0.dist-info/METADATA
ke_tidai_de_tuandui_lingxiu_peiyang_jihua-2024.3.1.0.dist-info/WHEEL
ke_tidai_de_tuandui_lingxiu_peiyang_jihua-2024.3.1.0.dist-info/entry_points.txt
ke_tidai_de_tuandui_lingxiu_peiyang_jihua-2024.3.1.0.dist-info/top_level.txt
ke_tidai_de_tuandui_lingxiu_peiyang_jihua-2024.3.1.0.dist-info/RECORD
